getsubstr/VERSION
getsubstr/__init__.py
getsubstr/main.py
getsubstr/setuptools.py
GetSubString-1.0.11.dist-info/LICENSE
GetSubString-1.0.11.dist-info/METADATA
GetSubString-1.0.11.dist-info/WHEEL
GetSubString-1.0.11.dist-info/entry_points.txt
GetSubString-1.0.11.dist-info/top_level.txt
GetSubString-1.0.11.dist-info/RECORD
