Metadata-Version: 2.1
Name: GetSubString
Version: 1.0.11
Summary: Get stdout line substring based on regexp.
Home-page: https://gitlab.com/alda78/getsubstr
Author: Ales Adamek
Author-email: alda78@seznam.cz
License: MIT
Classifier: Programming Language :: Python :: 3
Classifier: License :: OSI Approved :: MIT License
Classifier: Operating System :: OS Independent
Requires-Python: >=3.5
License-File: LICENSE
